boost_histogram/__init__.py
boost_histogram/_compat/__init__.py
boost_histogram/_compat/typing.py
boost_histogram/_core/__init__.pyi
boost_histogram/_core/accumulators.pyi
boost_histogram/_core/algorithm.pyi
boost_histogram/_core/axis/__init__.pyi
boost_histogram/_core/axis/transform.pyi
boost_histogram/_core/hist.pyi
boost_histogram/_core/storage.pyi
boost_histogram/_core.cpython-313-iphoneos.so
boost_histogram/_utils.py
boost_histogram/accumulators.py
boost_histogram/axis/__init__.py
boost_histogram/axis/transform.py
boost_histogram/histogram.py
boost_histogram/numpy.py
boost_histogram/py.typed
boost_histogram/serialization/__init__.py
boost_histogram/serialization/_axis.py
boost_histogram/serialization/_common.py
boost_histogram/serialization/_storage.py
boost_histogram/storage.py
boost_histogram/tag.py
boost_histogram/test.py
boost_histogram/typing.py
boost_histogram/version.py
boost_histogram/version.pyi
boost_histogram/view.py
boost_histogram-1.6.1.dist-info/METADATA
boost_histogram-1.6.1.dist-info/WHEEL
boost_histogram-1.6.1.dist-info/licenses/LICENSE
boost_histogram-1.6.1.dist-info/licenses/extern/histogram/LICENSE
boost_histogram-1.6.1.dist-info/RECORD
