Metadata-Version: 2.4
Name: boost-histogram
Version: 1.6.1
Summary: The Boost::Histogram Python wrapper.
Keywords: boost-histogram,histogram
Author-Email: Hans Dembinski <hans.dembinski@gmail.com>, Henry Schreiner <hschrein@cern.ch>
License-Expression: BSD-3-Clause AND BSL-1.0
License-File: extern/histogram/LICENSE
License-File: LICENSE
Classifier: Development Status :: 5 - Production/Stable
Classifier: Intended Audience :: Developers
Classifier: Intended Audience :: Information Technology
Classifier: Intended Audience :: Science/Research
Classifier: Operating System :: MacOS
Classifier: Operating System :: Microsoft :: Windows
Classifier: Operating System :: POSIX
Classifier: Operating System :: Unix
Classifier: Programming Language :: C++
Classifier: Programming Language :: Python :: 3 :: Only
Classifier: Programming Language :: Python :: 3
Classifier: Programming Language :: Python :: 3.10
Classifier: Programming Language :: Python :: 3.11
Classifier: Programming Language :: Python :: 3.12
Classifier: Programming Language :: Python :: 3.13
Classifier: Programming Language :: Python :: 3.14
Classifier: Programming Language :: Python :: 3.9
Classifier: Programming Language :: Python :: Free Threading :: 3 - Stable
Classifier: Programming Language :: Python :: Free Threading
Classifier: Programming Language :: Python :: Implementation :: CPython
Classifier: Programming Language :: Python :: Implementation :: PyPy
Classifier: Programming Language :: Python
Classifier: Topic :: Scientific/Engineering :: Information Analysis
Classifier: Topic :: Scientific/Engineering :: Mathematics
Classifier: Topic :: Scientific/Engineering :: Physics
Classifier: Topic :: Scientific/Engineering
Classifier: Topic :: Software Development
Classifier: Topic :: Utilities
Classifier: Typing :: Typed
Project-URL: Bug Tracker, https://github.com/scikit-hep/boost-histogram/issues
Project-URL: Changelog, https://boost-histogram.readthedocs.io/en/latest/CHANGELOG.html
Project-URL: Chat,  https://gitter.im/HSF/PyHEP-histogramming
Project-URL: Discussions, https://github.com/scikit-hep/boost-histogram/discussions
Project-URL: Documentation, https://boost-histogram.readthedocs.io/
Project-URL: Homepage, https://github.com/scikit-hep/boost-histogram
Requires-Python: >=3.9
Requires-Dist: numpy
